{"data":{"allPostTitles":{"edges":[{"node":{"fields":{"slug":"/dialog/draggable/","gcse":"014729256687841406486:qzbiyd0sri4"}}},{"node":{"fields":{"slug":"/dialog/getting-started/","gcse":"014729256687841406486:qzbiyd0sri4"}}},{"node":{"fields":{"slug":"/introduction/","gcse":"014729256687841406486:qzbiyd0sri4"}}},{"node":{"fields":{"slug":"/dialog/positioning/","gcse":"014729256687841406486:qzbiyd0sri4"}}},{"node":{"fields":{"slug":"/dialog/style/","gcse":"014729256687841406486:qzbiyd0sri4"}}},{"node":{"fields":{"slug":"/dialog/template/","gcse":"014729256687841406486:qzbiyd0sri4"}}},{"node":{"fields":{"slug":"/tooltip/content/","gcse":"014729256687841406486:qzbiyd0sri4"}}},{"node":{"fields":{"slug":"/tooltip/customization/","gcse":"014729256687841406486:qzbiyd0sri4"}}},{"node":{"fields":{"slug":"/tooltip/getting-started/","gcse":"014729256687841406486:qzbiyd0sri4"}}},{"node":{"fields":{"slug":"/tooltip/","gcse":"014729256687841406486:qzbiyd0sri4"}}},{"node":{"fields":{"slug":"/tooltip/open-mode/","gcse":"014729256687841406486:qzbiyd0sri4"}}},{"node":{"fields":{"slug":"/tooltip/position/","gcse":"014729256687841406486:qzbiyd0sri4"}}},{"node":{"fields":{"slug":"/tooltip/setting-dimension/","gcse":"014729256687841406486:qzbiyd0sri4"}}},{"node":{"fields":{"slug":"/dialog/how-to/achieve-two-way-binding-to-the-visible-property/","gcse":"014729256687841406486:qzbiyd0sri4"}}},{"node":{"fields":{"slug":"/dialog/how-to/add-an-icons-to-dialog-buttons/","gcse":"014729256687841406486:qzbiyd0sri4"}}},{"node":{"fields":{"slug":"/dialog/how-to/close-dialog-while-click-on-outside-of-dialog/","gcse":"014729256687841406486:qzbiyd0sri4"}}},{"node":{"fields":{"slug":"/dialog/how-to/create-nested-dialog/","gcse":"014729256687841406486:qzbiyd0sri4"}}},{"node":{"fields":{"slug":"/dialog/how-to/customize-the-dialog-appearance/","gcse":"014729256687841406486:qzbiyd0sri4"}}},{"node":{"fields":{"slug":"/dialog/how-to/display-a-dialog-with-custom-position/","gcse":"014729256687841406486:qzbiyd0sri4"}}},{"node":{"fields":{"slug":"/dialog/how-to/load-dialog-content-using-ajax/","gcse":"014729256687841406486:qzbiyd0sri4"}}},{"node":{"fields":{"slug":"/dialog/how-to/position-the-dialog-on-center-of-the-page-on-scrolling/","gcse":"014729256687841406486:qzbiyd0sri4"}}},{"node":{"fields":{"slug":"/dialog/how-to/prevent-closing-of-modal-dialog/","gcse":"014729256687841406486:qzbiyd0sri4"}}},{"node":{"fields":{"slug":"/dialog/how-to/prevent-opening-of-the-dialog/","gcse":"014729256687841406486:qzbiyd0sri4"}}},{"node":{"fields":{"slug":"/dialog/how-to/render-a-dialog-header-dynamically/","gcse":"014729256687841406486:qzbiyd0sri4"}}},{"node":{"fields":{"slug":"/dialog/how-to/render-a-dialog-without-header/","gcse":"014729256687841406486:qzbiyd0sri4"}}},{"node":{"fields":{"slug":"/dialog/how-to/show-dialog-with-fullscreen/","gcse":"014729256687841406486:qzbiyd0sri4"}}},{"node":{"fields":{"slug":"/dialog/localization/","gcse":"014729256687841406486:qzbiyd0sri4"}}},{"node":{"fields":{"slug":"/dialog/accessibility/","gcse":"014729256687841406486:qzbiyd0sri4"}}},{"node":{"fields":{"slug":"/dialog/animation/","gcse":"014729256687841406486:qzbiyd0sri4"}}}]},"postBySlug":{"html":"<h1 id=\"position-the-dialog-on-center-of-the-page-on-scrolling\"><a href=\"#position-the-dialog-on-center-of-the-page-on-scrolling\" aria-hidden class=\"anchor\"><svg aria-hidden=\"true\" height=\"16\" version=\"1.1\" viewBox=\"0 0 16 16\" width=\"16\"><path fill-rule=\"evenodd\" d=\"M4 9h1v1H4c-1.5 0-3-1.69-3-3.5S2.55 3 4 3h4c1.45 0 3 1.69 3 3.5 0 1.41-.91 2.72-2 3.25V8.59c.58-.45 1-1.27 1-2.09C10 5.22 8.98 4 8 4H4c-.98 0-2 1.22-2 2.5S3 9 4 9zm9-3h-1v1h1c1 0 2 1.22 2 2.5S13.98 12 13 12H9c-.98 0-2-1.22-2-2.5 0-.83.42-1.64 1-2.09V6.25c-1.09.53-2 1.84-2 3.25C6 11.31 7.55 13 9 13h4c1.45 0 3-1.69 3-3.5S14.5 6 13 6z\"></path></svg></a>Position the Dialog on center of the page on scrolling</h1>\n<p>By default, when you scroll the page/container, Dialog will also scroll along with the page/container.\nTo display the Dialog in the same position without scrolling, refer to the following code sample. Here added <code class=\"language-text\">e-fixed</code> class to Dialog element by using <code class=\"language-text\">CssClass</code> property and prevent the scrolling.</p>\n<div class=\"gatsby-highlight\" data-language=\"csharp\"><pre class=\"language-csharp\"><code class=\"language-csharp\">@<span class=\"token keyword\">using</span> Syncfusion<span class=\"token punctuation\">.</span>EJ2<span class=\"token punctuation\">.</span>Blazor\n@<span class=\"token keyword\">using</span> Syncfusion<span class=\"token punctuation\">.</span>EJ2<span class=\"token punctuation\">.</span>Blazor<span class=\"token punctuation\">.</span>Popups\n@<span class=\"token keyword\">using</span> Syncfusion<span class=\"token punctuation\">.</span>EJ2<span class=\"token punctuation\">.</span>Blazor<span class=\"token punctuation\">.</span>Buttons\n\n<span class=\"token operator\">&lt;</span>div<span class=\"token operator\">></span>\n    <span class=\"token operator\">&lt;</span>b<span class=\"token operator\">></span>JavaScript<span class=\"token punctuation\">:</span><span class=\"token operator\">&lt;</span><span class=\"token operator\">/</span>b<span class=\"token operator\">></span><span class=\"token operator\">&lt;</span>br <span class=\"token operator\">/</span><span class=\"token operator\">></span>\n    <span class=\"token class-name\">JavaScript</span> <span class=\"token keyword\">is</span> a high<span class=\"token operator\">-</span>level<span class=\"token punctuation\">,</span> <span class=\"token keyword\">dynamic</span><span class=\"token punctuation\">,</span> untyped<span class=\"token punctuation\">,</span> and interpreted programming language<span class=\"token punctuation\">.</span> <span class=\"token class-name\">It</span> has been standardized <span class=\"token keyword\">in</span> the <span class=\"token class-name\">ECMAScript</span>\n    language specification<span class=\"token punctuation\">.</span> <span class=\"token class-name\">Alongside</span> <span class=\"token class-name\">HTML</span> and CSS<span class=\"token punctuation\">,</span> it <span class=\"token keyword\">is</span> one of the three essential technologies of <span class=\"token class-name\">World</span> <span class=\"token class-name\">Wide</span> <span class=\"token class-name\">Web</span>\n    content production<span class=\"token punctuation\">;</span> the majority of websites employ it and it <span class=\"token keyword\">is</span> supported by all modern <span class=\"token class-name\">Web</span> browsers without\n    plug<span class=\"token operator\">-</span>ins<span class=\"token punctuation\">.</span> <span class=\"token class-name\">JavaScript</span> <span class=\"token keyword\">is</span> prototype<span class=\"token operator\">-</span>based with first<span class=\"token operator\">-</span><span class=\"token keyword\">class</span> functions<span class=\"token punctuation\">,</span> making it a multi<span class=\"token operator\">-</span>paradigm language<span class=\"token punctuation\">,</span> supporting\n    <span class=\"token keyword\">object</span> <span class=\"token operator\">-</span> oriented <span class=\"token punctuation\">,</span> imperative<span class=\"token punctuation\">,</span> and functional programming styles<span class=\"token punctuation\">.</span>\n    <span class=\"token operator\">&lt;</span>br <span class=\"token operator\">/</span><span class=\"token operator\">></span><span class=\"token operator\">&lt;</span>br <span class=\"token operator\">/</span><span class=\"token operator\">></span><span class=\"token operator\">&lt;</span>br <span class=\"token operator\">/</span><span class=\"token operator\">></span>\n    <span class=\"token operator\">&lt;</span>b<span class=\"token operator\">></span>MVC<span class=\"token punctuation\">:</span><span class=\"token operator\">&lt;</span><span class=\"token operator\">/</span>b<span class=\"token operator\">></span><span class=\"token operator\">&lt;</span>br <span class=\"token operator\">/</span><span class=\"token operator\">></span>\n    Model–view–controller <span class=\"token punctuation\">(</span>MVC<span class=\"token punctuation\">)</span> <span class=\"token keyword\">is</span> a software architecture pattern which separates the representation of information <span class=\"token keyword\">from</span> the user's interaction with it<span class=\"token punctuation\">.</span> <span class=\"token class-name\">The</span> model consists of application data<span class=\"token punctuation\">,</span> business rules<span class=\"token punctuation\">,</span> logic<span class=\"token punctuation\">,</span> and functions<span class=\"token punctuation\">.</span> <span class=\"token class-name\">A</span> view can be any output representation of data<span class=\"token punctuation\">,</span> such <span class=\"token keyword\">as</span> a chart or a diagram<span class=\"token punctuation\">.</span> <span class=\"token class-name\">Multiple</span> views of the same data are possible<span class=\"token punctuation\">,</span> such <span class=\"token keyword\">as</span> a bar chart <span class=\"token keyword\">for</span> management and a tabular view <span class=\"token keyword\">for</span> accountants<span class=\"token punctuation\">.</span> <span class=\"token class-name\">The</span> controller mediates input<span class=\"token punctuation\">,</span> converting it to commands <span class=\"token keyword\">for</span> the model or view<span class=\"token punctuation\">.</span><span class=\"token class-name\">The</span> central ideas behind <span class=\"token class-name\">MVC</span> are code reusability and <span class=\"token keyword\">in</span> addition to dividing the application <span class=\"token keyword\">into</span> three kinds of components<span class=\"token punctuation\">,</span> the <span class=\"token class-name\">MVC</span> design defines the interactions between them<span class=\"token punctuation\">.</span>\n    <span class=\"token class-name\">A</span> controller can send commands to its associated view to change the view<span class=\"token string\">'s presentation of the model (e.g., by scrolling through a document). It can also send commands to the model to update the model'</span>s state <span class=\"token punctuation\">(</span>e<span class=\"token punctuation\">.</span>g<span class=\"token punctuation\">.</span><span class=\"token punctuation\">,</span> editing a document<span class=\"token punctuation\">)</span><span class=\"token punctuation\">.</span>\n    <span class=\"token class-name\">A</span> model notifies its associated views and controllers when there has been a change <span class=\"token keyword\">in</span> its state<span class=\"token punctuation\">.</span> <span class=\"token class-name\">This</span> notification allows the views to produce updated output<span class=\"token punctuation\">,</span> and the controllers to change the available <span class=\"token keyword\">set</span> of commands<span class=\"token punctuation\">.</span> <span class=\"token class-name\">A</span> passive implementation of <span class=\"token class-name\">MVC</span> omits these notifications<span class=\"token punctuation\">,</span> because the application does not require them or the software platform does not support them<span class=\"token punctuation\">.</span>\n    <span class=\"token class-name\">A</span> view requests <span class=\"token keyword\">from</span> the model the information that it needs to generate an output representation to the user<span class=\"token punctuation\">.</span>\n<span class=\"token operator\">&lt;</span><span class=\"token operator\">/</span>div<span class=\"token operator\">></span>\n<span class=\"token operator\">&lt;</span><span class=\"token class-name\">EjsDialog</span> CssClass<span class=\"token operator\">=</span><span class=\"token string\">\"@DialogClass\"</span> Width<span class=\"token operator\">=</span><span class=\"token string\">\"250px\"</span> <span class=\"token operator\">></span>\n    <span class=\"token operator\">&lt;</span>DialogTemplates<span class=\"token operator\">></span>\n        <span class=\"token operator\">&lt;</span>Header<span class=\"token operator\">></span>Dialog<span class=\"token operator\">&lt;</span><span class=\"token operator\">/</span>Header<span class=\"token operator\">></span>\n        <span class=\"token operator\">&lt;</span>Content<span class=\"token operator\">></span> <span class=\"token operator\">&lt;</span>EjsButton @onclick<span class=\"token operator\">=</span><span class=\"token string\">'@OnClicked'</span> <span class=\"token operator\">></span><span class=\"token class-name\">Prevent</span> <span class=\"token class-name\">Dialog</span> Scroll<span class=\"token operator\">&lt;</span><span class=\"token operator\">/</span>EjsButton<span class=\"token operator\">></span><span class=\"token operator\">&lt;</span><span class=\"token operator\">/</span>Content<span class=\"token operator\">></span>\n    <span class=\"token operator\">&lt;</span><span class=\"token operator\">/</span>DialogTemplates<span class=\"token operator\">></span>\n<span class=\"token operator\">&lt;</span><span class=\"token operator\">/</span>EjsDialog<span class=\"token operator\">></span>\n\n<span class=\"token operator\">&lt;</span>style<span class=\"token operator\">></span>\n    body <span class=\"token punctuation\">{</span>\n        overflow<span class=\"token operator\">-</span>y<span class=\"token punctuation\">:</span> scroll<span class=\"token punctuation\">;</span>\n    <span class=\"token punctuation\">}</span>\n    <span class=\"token punctuation\">.</span>e<span class=\"token operator\">-</span><span class=\"token keyword\">fixed</span> <span class=\"token punctuation\">{</span>\n        position<span class=\"token punctuation\">:</span> <span class=\"token keyword\">fixed</span><span class=\"token punctuation\">;</span>\n    <span class=\"token punctuation\">}</span>\n<span class=\"token operator\">&lt;</span><span class=\"token operator\">/</span>style<span class=\"token operator\">></span>\n\n@code <span class=\"token punctuation\">{</span>\n    <span class=\"token keyword\">public</span> <span class=\"token keyword\">string</span> DialogClass <span class=\"token punctuation\">{</span> <span class=\"token keyword\">get</span><span class=\"token punctuation\">;</span> <span class=\"token keyword\">set</span><span class=\"token punctuation\">;</span> <span class=\"token punctuation\">}</span>\n\n    <span class=\"token keyword\">private</span> <span class=\"token keyword\">void</span> <span class=\"token function\">OnClicked</span><span class=\"token punctuation\">(</span><span class=\"token punctuation\">)</span> <span class=\"token punctuation\">{</span>\n        <span class=\"token keyword\">this</span><span class=\"token punctuation\">.</span>DialogClass <span class=\"token operator\">=</span> <span class=\"token string\">\"e-fixed\"</span><span class=\"token punctuation\">;</span>\n        <span class=\"token keyword\">this</span><span class=\"token punctuation\">.</span><span class=\"token function\">StateHasChanged</span><span class=\"token punctuation\">(</span><span class=\"token punctuation\">)</span><span class=\"token punctuation\">;</span>\n    <span class=\"token punctuation\">}</span>\n<span class=\"token punctuation\">}</span></code></pre></div>","timeToRead":2,"excerpt":"Position the Dialog on center of the page on scrolling By default, when you scroll the page/container, Dialog will also scroll along with…","fields":{"slug":"/dialog/how-to/position-the-dialog-on-center-of-the-page-on-scrolling/","gcse":"014729256687841406486:qzbiyd0sri4"}}},"pageContext":{"slug":"/dialog/how-to/position-the-dialog-on-center-of-the-page-on-scrolling/","previous":{"html":"<h1 id=\"prevent-closing-of-modal-dialog\"><a href=\"#prevent-closing-of-modal-dialog\" aria-hidden class=\"anchor\"><svg aria-hidden=\"true\" height=\"16\" version=\"1.1\" viewBox=\"0 0 16 16\" width=\"16\"><path fill-rule=\"evenodd\" d=\"M4 9h1v1H4c-1.5 0-3-1.69-3-3.5S2.55 3 4 3h4c1.45 0 3 1.69 3 3.5 0 1.41-.91 2.72-2 3.25V8.59c.58-.45 1-1.27 1-2.09C10 5.22 8.98 4 8 4H4c-.98 0-2 1.22-2 2.5S3 9 4 9zm9-3h-1v1h1c1 0 2 1.22 2 2.5S13.98 12 13 12H9c-.98 0-2-1.22-2-2.5 0-.83.42-1.64 1-2.09V6.25c-1.09.53-2 1.84-2 3.25C6 11.31 7.55 13 9 13h4c1.45 0 3-1.69 3-3.5S14.5 6 13 6z\"></path></svg></a>Prevent closing of modal dialog</h1>\n<p>You can prevent closing of modal dialog by setting the <code class=\"language-text\">OnClose</code> event argument cancel value to true.\nIn the following sample, the dialog is closed when you enter the username value with minimum 4 characters. Otherwise, it will not be closed.</p>\n<div class=\"gatsby-highlight\" data-language=\"csharp\"><pre class=\"language-csharp\"><code class=\"language-csharp\">@<span class=\"token keyword\">using</span> Syncfusion<span class=\"token punctuation\">.</span>EJ2<span class=\"token punctuation\">.</span>Blazor\n@<span class=\"token keyword\">using</span> Syncfusion<span class=\"token punctuation\">.</span>EJ2<span class=\"token punctuation\">.</span>Blazor<span class=\"token punctuation\">.</span>Popups\n@<span class=\"token keyword\">using</span> Syncfusion<span class=\"token punctuation\">.</span>EJ2<span class=\"token punctuation\">.</span>Blazor<span class=\"token punctuation\">.</span>Buttons\n\n<span class=\"token operator\">&lt;</span>EjsButton @onclick<span class=\"token operator\">=</span><span class=\"token string\">\"@OnClicked\"</span><span class=\"token operator\">></span><span class=\"token class-name\">Open</span> Dialog<span class=\"token operator\">&lt;</span><span class=\"token operator\">/</span>EjsButton<span class=\"token operator\">></span>\n<span class=\"token operator\">&lt;</span>EjsDialog @bind<span class=\"token operator\">-</span>Visible<span class=\"token operator\">=</span><span class=\"token string\">\"@isVisible\"</span> ID<span class=\"token operator\">=</span><span class=\"token string\">\"dialog\"</span> IsModal<span class=\"token operator\">=</span><span class=\"token string\">\"true\"</span> Width<span class=\"token operator\">=</span><span class=\"token string\">\"300px\"</span><span class=\"token operator\">></span>\n    <span class=\"token operator\">&lt;</span><span class=\"token class-name\">DialogEvents</span> OnClose<span class=\"token operator\">=</span><span class=\"token string\">\"Validation\"</span><span class=\"token operator\">></span><span class=\"token operator\">&lt;</span><span class=\"token operator\">/</span>DialogEvents<span class=\"token operator\">></span>\n    <span class=\"token operator\">&lt;</span>DialogTemplates<span class=\"token operator\">></span>\n        <span class=\"token operator\">&lt;</span>Header<span class=\"token operator\">></span> <span class=\"token operator\">&lt;</span>div id<span class=\"token operator\">=</span><span class=\"token string\">\"heading\"</span><span class=\"token operator\">></span><span class=\"token class-name\">Sign</span> <span class=\"token keyword\">in</span><span class=\"token operator\">&lt;</span><span class=\"token operator\">/</span>div<span class=\"token operator\">></span> <span class=\"token operator\">&lt;</span><span class=\"token operator\">/</span>Header<span class=\"token operator\">></span>\n        <span class=\"token operator\">&lt;</span>Content<span class=\"token operator\">></span>\n            <span class=\"token operator\">&lt;</span>div id<span class=\"token operator\">=</span><span class=\"token string\">'input-container'</span><span class=\"token operator\">></span>\n                <span class=\"token operator\">&lt;</span>div <span class=\"token keyword\">class</span><span class=\"token operator\">=</span><span class=\"token string\">\"e-float-input e-input-group\"</span><span class=\"token operator\">></span>\n                    <span class=\"token operator\">&lt;</span>input id<span class=\"token operator\">=</span><span class=\"token string\">\"username\"</span> required<span class=\"token operator\">=</span><span class=\"token string\">\"\"</span> type<span class=\"token operator\">=</span><span class=\"token string\">\"text\"</span> @bind<span class=\"token operator\">=</span><span class=\"token string\">\"@Textvalue\"</span> <span class=\"token operator\">/</span><span class=\"token operator\">></span>\n                    <span class=\"token operator\">&lt;</span>span <span class=\"token keyword\">class</span><span class=\"token operator\">=</span><span class=\"token string\">\"e-float-line\"</span><span class=\"token operator\">></span><span class=\"token operator\">&lt;</span><span class=\"token operator\">/</span>span<span class=\"token operator\">></span>\n                    <span class=\"token operator\">&lt;</span>label <span class=\"token keyword\">class</span><span class=\"token operator\">=</span><span class=\"token string\">\"e-float-text\"</span><span class=\"token operator\">></span>Username<span class=\"token operator\">&lt;</span><span class=\"token operator\">/</span>label<span class=\"token operator\">></span>\n                <span class=\"token operator\">&lt;</span><span class=\"token operator\">/</span>div<span class=\"token operator\">></span>\n            <span class=\"token operator\">&lt;</span><span class=\"token operator\">/</span>div<span class=\"token operator\">></span>\n            <span class=\"token operator\">&lt;</span>div <span class=\"token keyword\">class</span><span class=\"token operator\">=</span><span class=\"token string\">'form-group'</span><span class=\"token operator\">></span>\n                <span class=\"token operator\">&lt;</span>div <span class=\"token keyword\">class</span><span class=\"token operator\">=</span><span class=\"token string\">\"e-float-input e-input-group\"</span><span class=\"token operator\">></span>\n                    <span class=\"token operator\">&lt;</span>input id<span class=\"token operator\">=</span><span class=\"token string\">\"username\"</span> required<span class=\"token operator\">=</span><span class=\"token string\">\"\"</span> type<span class=\"token operator\">=</span><span class=\"token string\">\"text\"</span> @bind<span class=\"token operator\">=</span><span class=\"token string\">\"@Textvalue2\"</span> <span class=\"token operator\">/</span><span class=\"token operator\">></span>\n                    <span class=\"token operator\">&lt;</span>span <span class=\"token keyword\">class</span><span class=\"token operator\">=</span><span class=\"token string\">\"e-float-line\"</span><span class=\"token operator\">></span><span class=\"token operator\">&lt;</span><span class=\"token operator\">/</span>span<span class=\"token operator\">></span>\n                    <span class=\"token operator\">&lt;</span>label <span class=\"token keyword\">class</span><span class=\"token operator\">=</span><span class=\"token string\">\"e-float-text\"</span><span class=\"token operator\">></span>Password<span class=\"token operator\">&lt;</span><span class=\"token operator\">/</span>label<span class=\"token operator\">></span>\n                <span class=\"token operator\">&lt;</span><span class=\"token operator\">/</span>div<span class=\"token operator\">></span>\n            <span class=\"token operator\">&lt;</span><span class=\"token operator\">/</span>div<span class=\"token operator\">></span>\n        <span class=\"token operator\">&lt;</span><span class=\"token operator\">/</span>Content<span class=\"token operator\">></span>\n    <span class=\"token operator\">&lt;</span><span class=\"token operator\">/</span>DialogTemplates<span class=\"token operator\">></span>\n    <span class=\"token operator\">&lt;</span>DialogButtons<span class=\"token operator\">></span>\n        <span class=\"token operator\">&lt;</span><span class=\"token class-name\">DialogButton</span> OnClick<span class=\"token operator\">=</span><span class=\"token string\">\"@OnClick\"</span><span class=\"token operator\">></span>\n            <span class=\"token operator\">&lt;</span><span class=\"token class-name\">DialogButtonModel</span> Content<span class=\"token operator\">=</span><span class=\"token string\">\"Log in\"</span> IsPrimary<span class=\"token operator\">=</span><span class=\"token string\">\"true\"</span><span class=\"token operator\">></span><span class=\"token operator\">&lt;</span><span class=\"token operator\">/</span>DialogButtonModel<span class=\"token operator\">></span>\n        <span class=\"token operator\">&lt;</span><span class=\"token operator\">/</span>DialogButton<span class=\"token operator\">></span>\n    <span class=\"token operator\">&lt;</span><span class=\"token operator\">/</span>DialogButtons<span class=\"token operator\">></span>\n<span class=\"token operator\">&lt;</span><span class=\"token operator\">/</span>EjsDialog<span class=\"token operator\">></span>\n\n<span class=\"token operator\">&lt;</span>style<span class=\"token operator\">></span>\n    <span class=\"token preprocessor property\">#dialog.e-dialog .e-dlg-header-content .e-dlg-header {</span>\n        text<span class=\"token operator\">-</span>align<span class=\"token punctuation\">:</span> center<span class=\"token punctuation\">;</span>\n        width<span class=\"token punctuation\">:</span><span class=\"token number\">100</span><span class=\"token operator\">%</span><span class=\"token punctuation\">;</span>\n        color<span class=\"token punctuation\">:</span> #<span class=\"token number\">333</span><span class=\"token punctuation\">;</span>\n        font<span class=\"token operator\">-</span>weight<span class=\"token punctuation\">:</span> bold<span class=\"token punctuation\">;</span>\n        font<span class=\"token operator\">-</span>size<span class=\"token punctuation\">:</span> <span class=\"token number\">20</span>px<span class=\"token punctuation\">;</span>\n    <span class=\"token punctuation\">}</span>\n    <span class=\"token preprocessor property\">#input-container .e-float-input { </span><span class=\"token comment\">/* csslint allow: adjoining-classes */</span>\n      margin<span class=\"token punctuation\">:</span> <span class=\"token number\">17</span>px <span class=\"token number\">0</span><span class=\"token punctuation\">;</span>\n    <span class=\"token punctuation\">}</span>\n    <span class=\"token punctuation\">.</span>e<span class=\"token operator\">-</span>footer<span class=\"token operator\">-</span>content <span class=\"token punctuation\">{</span>\n        padding<span class=\"token punctuation\">:</span> <span class=\"token number\">20</span>px <span class=\"token number\">0</span> <span class=\"token number\">0</span><span class=\"token punctuation\">;</span>\n        width<span class=\"token punctuation\">:</span> <span class=\"token number\">100</span><span class=\"token operator\">%</span><span class=\"token punctuation\">;</span>\n    <span class=\"token punctuation\">}</span>\n    <span class=\"token punctuation\">.</span>e<span class=\"token operator\">-</span>dialog <span class=\"token punctuation\">.</span>e<span class=\"token operator\">-</span>footer<span class=\"token operator\">-</span>content <span class=\"token punctuation\">.</span>e<span class=\"token operator\">-</span>btn <span class=\"token punctuation\">{</span>\n        width<span class=\"token punctuation\">:</span> <span class=\"token number\">100</span><span class=\"token operator\">%</span><span class=\"token punctuation\">;</span>\n        height<span class=\"token punctuation\">:</span> <span class=\"token number\">36</span>px<span class=\"token punctuation\">;</span>\n    <span class=\"token punctuation\">}</span>\n    <span class=\"token preprocessor property\">#heading {</span>\n        color<span class=\"token punctuation\">:</span> #<span class=\"token number\">333</span><span class=\"token punctuation\">;</span>\n        font<span class=\"token operator\">-</span>weight<span class=\"token punctuation\">:</span> bold<span class=\"token punctuation\">;</span>\n        margin<span class=\"token punctuation\">:</span> <span class=\"token number\">0</span> <span class=\"token number\">0</span> <span class=\"token number\">15</span>px<span class=\"token punctuation\">;</span>\n        text<span class=\"token operator\">-</span>align<span class=\"token punctuation\">:</span> center<span class=\"token punctuation\">;</span>\n        font<span class=\"token operator\">-</span>size<span class=\"token punctuation\">:</span> <span class=\"token number\">20</span>px<span class=\"token punctuation\">;</span>\n    <span class=\"token punctuation\">}</span>\n    <span class=\"token preprocessor property\">#dialog.e-dialog .e-footer-content {</span>\n        padding<span class=\"token punctuation\">:</span> <span class=\"token number\">0</span> <span class=\"token number\">18</span>px <span class=\"token number\">18</span>px<span class=\"token punctuation\">;</span>\n    <span class=\"token punctuation\">}</span>\n    <span class=\"token preprocessor property\">#dialog.e-dialog .e-footer-content .e-btn {</span>\n        margin<span class=\"token operator\">-</span>left<span class=\"token punctuation\">:</span> <span class=\"token number\">0</span><span class=\"token punctuation\">;</span>\n    <span class=\"token punctuation\">}</span>\n<span class=\"token operator\">&lt;</span><span class=\"token operator\">/</span>style<span class=\"token operator\">></span>\n\n@code <span class=\"token punctuation\">{</span>\n    <span class=\"token keyword\">private</span> <span class=\"token keyword\">bool</span> isVisible <span class=\"token punctuation\">{</span> <span class=\"token keyword\">get</span><span class=\"token punctuation\">;</span> <span class=\"token keyword\">set</span><span class=\"token punctuation\">;</span> <span class=\"token punctuation\">}</span> <span class=\"token operator\">=</span> <span class=\"token keyword\">true</span><span class=\"token punctuation\">;</span>\n    <span class=\"token keyword\">private</span> <span class=\"token keyword\">string</span> Textvalue <span class=\"token punctuation\">{</span> <span class=\"token keyword\">get</span><span class=\"token punctuation\">;</span> <span class=\"token keyword\">set</span><span class=\"token punctuation\">;</span> <span class=\"token punctuation\">}</span> <span class=\"token operator\">=</span> <span class=\"token string\">\"\"</span><span class=\"token punctuation\">;</span>\n    <span class=\"token keyword\">private</span> <span class=\"token keyword\">string</span> Textvalue2 <span class=\"token punctuation\">{</span> <span class=\"token keyword\">get</span><span class=\"token punctuation\">;</span> <span class=\"token keyword\">set</span><span class=\"token punctuation\">;</span> <span class=\"token punctuation\">}</span> <span class=\"token operator\">=</span> <span class=\"token string\">\"\"</span><span class=\"token punctuation\">;</span>\n\n    <span class=\"token keyword\">private</span> <span class=\"token keyword\">void</span> <span class=\"token function\">OnClick</span><span class=\"token punctuation\">(</span><span class=\"token punctuation\">)</span>\n    <span class=\"token punctuation\">{</span>\n        <span class=\"token keyword\">this</span><span class=\"token punctuation\">.</span>isVisible <span class=\"token operator\">=</span> <span class=\"token keyword\">false</span><span class=\"token punctuation\">;</span>\n    <span class=\"token punctuation\">}</span>\n\n    <span class=\"token keyword\">private</span> <span class=\"token keyword\">void</span> <span class=\"token function\">OnClicked</span><span class=\"token punctuation\">(</span><span class=\"token punctuation\">)</span>\n    <span class=\"token punctuation\">{</span>\n        <span class=\"token keyword\">this</span><span class=\"token punctuation\">.</span>isVisible <span class=\"token operator\">=</span> <span class=\"token keyword\">true</span><span class=\"token punctuation\">;</span>\n    <span class=\"token punctuation\">}</span>\n\n    <span class=\"token keyword\">private</span> <span class=\"token keyword\">void</span> <span class=\"token function\">Validation</span><span class=\"token punctuation\">(</span><span class=\"token class-name\">BeforeCloseEventArgs</span> args<span class=\"token punctuation\">)</span>\n    <span class=\"token punctuation\">{</span>\n        <span class=\"token keyword\">if</span> <span class=\"token punctuation\">(</span>Textvalue <span class=\"token operator\">==</span> <span class=\"token string\">\"\"</span> <span class=\"token operator\">&amp;&amp;</span> Textvalue2 <span class=\"token operator\">==</span> <span class=\"token string\">\"\"</span><span class=\"token punctuation\">)</span>\n        <span class=\"token punctuation\">{</span>\n            args<span class=\"token punctuation\">.</span>Cancel <span class=\"token operator\">=</span> <span class=\"token keyword\">true</span><span class=\"token punctuation\">;</span>\n            System<span class=\"token punctuation\">.</span>Diagnostics<span class=\"token punctuation\">.</span>Debug<span class=\"token punctuation\">.</span><span class=\"token function\">WriteLine</span><span class=\"token punctuation\">(</span><span class=\"token string\">\"Enter the Username and Password\"</span><span class=\"token punctuation\">)</span><span class=\"token punctuation\">;</span>\n        <span class=\"token punctuation\">}</span> <span class=\"token keyword\">else</span> <span class=\"token keyword\">if</span> <span class=\"token punctuation\">(</span>Textvalue <span class=\"token operator\">==</span> <span class=\"token string\">\"\"</span><span class=\"token punctuation\">)</span> <span class=\"token punctuation\">{</span>\n            args<span class=\"token punctuation\">.</span>Cancel<span class=\"token operator\">=</span> <span class=\"token keyword\">true</span><span class=\"token punctuation\">;</span>\n            System<span class=\"token punctuation\">.</span>Diagnostics<span class=\"token punctuation\">.</span>Debug<span class=\"token punctuation\">.</span><span class=\"token function\">WriteLine</span><span class=\"token punctuation\">(</span><span class=\"token string\">\"Enter the username\"</span><span class=\"token punctuation\">)</span><span class=\"token punctuation\">;</span>\n        <span class=\"token punctuation\">}</span> <span class=\"token keyword\">else</span> <span class=\"token keyword\">if</span> <span class=\"token punctuation\">(</span>Textvalue2 <span class=\"token operator\">==</span> <span class=\"token string\">\"\"</span><span class=\"token punctuation\">)</span> <span class=\"token punctuation\">{</span>\n            args<span class=\"token punctuation\">.</span>Cancel<span class=\"token operator\">=</span> <span class=\"token keyword\">true</span><span class=\"token punctuation\">;</span>\n            System<span class=\"token punctuation\">.</span>Diagnostics<span class=\"token punctuation\">.</span>Debug<span class=\"token punctuation\">.</span><span class=\"token function\">WriteLine</span><span class=\"token punctuation\">(</span><span class=\"token string\">\"Enter the password\"</span><span class=\"token punctuation\">)</span><span class=\"token punctuation\">;</span>\n        <span class=\"token punctuation\">}</span> <span class=\"token keyword\">else</span> <span class=\"token keyword\">if</span> <span class=\"token punctuation\">(</span>Textvalue<span class=\"token punctuation\">.</span>Length <span class=\"token operator\">&lt;</span> <span class=\"token number\">4</span><span class=\"token punctuation\">)</span> <span class=\"token punctuation\">{</span>\n            args<span class=\"token punctuation\">.</span>Cancel<span class=\"token operator\">=</span> <span class=\"token keyword\">true</span><span class=\"token punctuation\">;</span>\n            System<span class=\"token punctuation\">.</span>Diagnostics<span class=\"token punctuation\">.</span>Debug<span class=\"token punctuation\">.</span><span class=\"token function\">WriteLine</span><span class=\"token punctuation\">(</span><span class=\"token string\">\"Username must be minimum 4 characters\"</span><span class=\"token punctuation\">)</span><span class=\"token punctuation\">;</span>\n        <span class=\"token punctuation\">}</span> <span class=\"token keyword\">else</span> <span class=\"token punctuation\">{</span>\n            args<span class=\"token punctuation\">.</span>Cancel<span class=\"token operator\">=</span> <span class=\"token keyword\">false</span><span class=\"token punctuation\">;</span>\n            Textvalue <span class=\"token operator\">=</span> <span class=\"token string\">\"\"</span><span class=\"token punctuation\">;</span>\n            Textvalue2 <span class=\"token operator\">=</span> <span class=\"token string\">\"\"</span><span class=\"token punctuation\">;</span>\n        <span class=\"token punctuation\">}</span>\n    <span class=\"token punctuation\">}</span></code></pre></div>\n<p>The output will be as follows.</p>\n<p><img src=\"/production/blazor/documentation/dialog/images/prevent-dialog.png\" alt=\"dialog\"></p>","id":"97da300b-007d-5818-bd9e-ab08b316de90","fields":{"slug":"/dialog/how-to/prevent-closing-of-modal-dialog/","parentPath":"dialog/how-to","childPath":"prevent-closing-of-modal-dialog","gcse":"014729256687841406486:qzbiyd0sri4","header":"","breadCrumb":"Dialog/How To/Prevent closing of modal Dialog","isReleaseNotes":false,"title":"How to Prevent closing of modal Dialog in Blazor [Preview] Dialog component - Syncfusion","description":"Checkout and learn about Prevent closing of modal Dialog in Blazor [Preview] Dialog component of Syncfusion Essential JS 2, and more details.","platform":"Blazor [Preview]","isRobots":true}},"next":{"html":"<h1 id=\"load-dialog-content-using-ajax\"><a href=\"#load-dialog-content-using-ajax\" aria-hidden class=\"anchor\"><svg aria-hidden=\"true\" height=\"16\" version=\"1.1\" viewBox=\"0 0 16 16\" width=\"16\"><path fill-rule=\"evenodd\" d=\"M4 9h1v1H4c-1.5 0-3-1.69-3-3.5S2.55 3 4 3h4c1.45 0 3 1.69 3 3.5 0 1.41-.91 2.72-2 3.25V8.59c.58-.45 1-1.27 1-2.09C10 5.22 8.98 4 8 4H4c-.98 0-2 1.22-2 2.5S3 9 4 9zm9-3h-1v1h1c1 0 2 1.22 2 2.5S13.98 12 13 12H9c-.98 0-2-1.22-2-2.5 0-.83.42-1.64 1-2.09V6.25c-1.09.53-2 1.84-2 3.25C6 11.31 7.55 13 9 13h4c1.45 0 3-1.69 3-3.5S14.5 6 13 6z\"></path></svg></a>Load dialog content using AJAX</h1>\n<p>You can load the dialog’s content dynamically from external source like external file using AJAX library.\nThe AJAX library can make the request and load dialog’s content using its <code class=\"language-text\">success</code> event.</p>","id":"5a6879ac-0fc5-5a73-bba8-fc199adc888c","fields":{"slug":"/dialog/how-to/load-dialog-content-using-ajax/","parentPath":"dialog/how-to","childPath":"load-dialog-content-using-ajax","gcse":"014729256687841406486:qzbiyd0sri4","header":"","breadCrumb":"Dialog/How To/","isReleaseNotes":false,"title":"Blazor [Preview]  component - Syncfusion","description":"Checkout and learn about getting started with Blazor [Preview]  component of Syncfusion Essential JS 2, and more details.","platform":"Blazor [Preview]","isRobots":true}},"gcse":"014729256687841406486:qzbiyd0sri4","header":"","breadCrumb":"Dialog/How To/Position the Dialog in center of the page on scrolling","isReleaseNotes":false,"title":"How to Position the Dialog in center of the page on scrolling in Blazor [Preview] Dialog component - Syncfusion","description":"Checkout and learn about Position the Dialog in center of the page on scrolling in Blazor [Preview] Dialog component of Syncfusion Essential JS 2, and more details.","platform":"Blazor [Preview]","isRobots":true}}